pivot/__init__.py
pivot/cli.py
pypivot-0.1.4.dist-info/entry_points.txt
pypivot-0.1.4.dist-info/LICENSE
pypivot-0.1.4.dist-info/WHEEL
pypivot-0.1.4.dist-info/METADATA
pypivot-0.1.4.dist-info/RECORD
