Metadata-Version: 2.1
Name: pypivot
Version: 0.1.4
Summary: Pivot, unpivot, melt, and tranform data
Author-email: Carl Anderson <carl@dumpsterfire.dev>
Project-URL: repository, https://github.com/barabo/pivot
